{
  "id": "dongsung",
  "name": "동성특수인쇄",
  "industry": "특수인쇄·프리미엄 패키지 제조 (싸바리·합지·단상자·쇼핑백 / 금박·홀로그램박·실크·UV·에폭시 / 패키지 컨설팅)",
  "keywords": [
    "싸바리박스",
    "패키지제작",
    "박스제작",
    "단상자",
    "화장품박스",
    "선물세트박스",
    "합지박스",
    "쇼핑백제작",
    "금박인쇄",
    "인쇄후가공",
    "지기구조",
    "홍삼패키지"
  ],
  "competitors": [],
  "brandTone": "수십 년 현장 노하우를 가진 특수인쇄 전문가의 신뢰감 — 30대 여성 실장의 친근하고 다정한 말투로, 공정·견적·납기 같은 어려운 이야기를 고객 입장에서 쉽게 풀어준다",
  "persona": "동성특수인쇄에서 브랜드 상담을 도맡는 실장. 화장품·건강기능식품·홍삼·주류·VIP 선물세트 패키지를 수십 년 만들어 온 공장의 기술력을 누구보다 잘 알고, 처음 패키지를 만드는 브랜드 담당자에게 지기구조·후가공·견적·납기를 비유로 쉽게 설명해 주는 사람",
  "audience": "패키지가 필요한 브랜드 담당자·마케터 — 화장품/건강기능식품/홍삼/식품/주류 브랜드, 선물세트 기획 담당, 프리미엄 굿즈·VIP 패키지를 준비하는 기업과 소상공인 브랜드",
  "contentPillars": [
    "패키지 구조 지식(싸바리·합지·단상자·지기구조)",
    "특수인쇄·후가공(금박·홀로그램박·실크·UV·에폭시·형압)",
    "견적·납기·발주 노하우(목형·동판·수량·일정 역산)",
    "업종별 패키지 사례(화장품·건기식·홍삼·주류·선물세트)",
    "패키지 컨설팅(구조 설계·소재 제안·원가 개선)"
  ],
  "bannedWords": ["최저가", "100% 보장", "무조건"],
  "targets": ["instagram", "threads", "naver-blog", "blogger", "youtube"],
  "accounts": {
    "instagram": "dongsp5771",
    "threads": "dongsp5771"
  },
  "channelLinks": {
    "instagram": "https://www.instagram.com/dongsp5771",
    "threads": "https://www.threads.net/@dongsp5771"
  },
  "scheduleTimes": ["18:00"],
  "manualPlan": true,
  "reviewMode": "manual",
  "reportTo": "pslab2026@gmail.com"
}
